easy_vqe/__init__.py
easy_vqe/circuit.py
easy_vqe/hamiltonian.py
easy_vqe/measurement.py
easy_vqe/visualization.py
easy_vqe/vqe_core.py
easy_vqe-1.2.0.dist-info/licenses/LICENSE
easy_vqe-1.2.0.dist-info/METADATA
easy_vqe-1.2.0.dist-info/WHEEL
easy_vqe-1.2.0.dist-info/top_level.txt
easy_vqe-1.2.0.dist-info/RECORD
